{
    "id": "hoadao",
    "url": "https://tt.8share.pro/buncha",
    "name": "Hoa Đào TV",
    "color": "#1cb57a",
    "image": {
        "url": "https://raw.githubusercontent.com/nkqbbg/20251_CNWeb_User_Management/7c0829f097849f9cfc54b5f6f37e2dbddda468c6/hoadaologo.jpg"
    },
    "description": "Hoa Đào TV - Trang web phát sóng bóng đá trực tuyến miễn phí hàng đầu tại Việt Nam, mang đến trải nghiệm chất lượng cao với bình luận tiếng Việt sống động.",
    "share": {
        "url": "https://tt.8share.pro/buncha"
    },
    "notice": {
        "closeable": true,
        "icon": "https://media.hth4nh.eu.org/static/img/tele.png",
        "id": "notice",
        "link": "https://t.me/dqstore1",
        "text": "Nhóm Telegram cập nhật"
    },
    "groups": [
        {
            "id": "live",
            "name": "🔴 Live",
            "display": "horizontal",
            "grid_number": 1,
            "channels": [
                {
                    "id": "ch-bc2558e51b14",
                    "name": "havre-athletic-club-vs-paris-saint-germain-2397996",
                    "labels": [
                        {
                            "position": "top-left",
                            "text": "● Live",
                            "color": "#FF0000",
                            "text_color": "#FFFFFF"
                        }
                    ],
                    "description": "Live Stream",
                    "image": {
                        "url": "https://raw.githubusercontent.com/nkqbbg/20251_CNWeb_User_Management/7c0829f097849f9cfc54b5f6f37e2dbddda468c6/hoadaologo.jpg",
                        "height": 480,
                        "width": 640,
                        "display": "cover",
                        "shape": "square"
                    },
                    "type": "single",
                    "display": "text-below",
                    "sources": [
                        {
                            "id": "src-66bbfcdf86ab",
                            "name": "Server 1",
                            "contents": [
                                {
                                    "id": "ct-04c409628d0e",
                                    "name": "havre-athletic-club-vs-paris-saint-germain-2397996",
                                    "streams": [
                                        {
                                            "id": "st-417f22656c78",
                                            "name": "Server 1",
                                            "stream_links": [
                                                {
                                                    "id": "lnk-0fb7cf5da11c",
                                                    "name": "HD",
                                                    "type": "hls",
                                                    "default": true,
                                                    "url": "https://live10.watchsoccerlivenews.net/live/chimnho_key/playlist.m3u8",
                                                    "request_headers": [
                                                        {
                                                            "key": "Referer",
                                                            "value": "https://hoadaotv.org/havre-athletic-club-vs-paris-saint-germain-2397996"
                                                        },
                                                        {
                                                            "key": "User-Agent",
                                                            "value": "Mozilla/5.0"
                                                        }
                                                    ]
                                                }
                                            ]
                                        }
                                    ]
                                }
                            ]
                        }
                    ]
                },
                {
                    "id": "ch-40df5601dad9",
                    "name": "the-cong-viettel-vs-hanoi-fc-2398352",
                    "labels": [
                        {
                            "position": "top-left",
                            "text": "● Live",
                            "color": "#FF0000",
                            "text_color": "#FFFFFF"
                        }
                    ],
                    "description": "Live Stream",
                    "image": {
                        "url": "https://raw.githubusercontent.com/nkqbbg/20251_CNWeb_User_Management/7c0829f097849f9cfc54b5f6f37e2dbddda468c6/hoadaologo.jpg",
                        "height": 480,
                        "width": 640,
                        "display": "cover",
                        "shape": "square"
                    },
                    "type": "single",
                    "display": "text-below",
                    "sources": [
                        {
                            "id": "src-16ab451385f7",
                            "name": "Server 1",
                            "contents": [
                                {
                                    "id": "ct-013f402c1928",
                                    "name": "the-cong-viettel-vs-hanoi-fc-2398352",
                                    "streams": [
                                        {
                                            "id": "st-9693539f5c84",
                                            "name": "Server 1",
                                            "stream_links": [
                                                {
                                                    "id": "lnk-d801dcc7ba86",
                                                    "name": "HD",
                                                    "type": "hls",
                                                    "default": true,
                                                    "url": "https://live10.watchsoccerlivenews.net/live/chaoquay/playlist.m3u8",
                                                    "request_headers": [
                                                        {
                                                            "key": "Referer",
                                                            "value": "https://hoadaotv.org/the-cong-viettel-vs-hanoi-fc-2398352"
                                                        },
                                                        {
                                                            "key": "User-Agent",
                                                            "value": "Mozilla/5.0"
                                                        }
                                                    ]
                                                }
                                            ]
                                        }
                                    ]
                                }
                            ]
                        }
                    ]
                },
                {
                    "id": "ch-159fc3e3a270",
                    "name": "cong-an-ho-chi-minh-city-vs-becamex-ho-chi-minh-city-2398356",
                    "labels": [
                        {
                            "position": "top-left",
                            "text": "● Live",
                            "color": "#FF0000",
                            "text_color": "#FFFFFF"
                        }
                    ],
                    "description": "Live Stream",
                    "image": {
                        "url": "https://raw.githubusercontent.com/nkqbbg/20251_CNWeb_User_Management/7c0829f097849f9cfc54b5f6f37e2dbddda468c6/hoadaologo.jpg",
                        "height": 480,
                        "width": 640,
                        "display": "cover",
                        "shape": "square"
                    },
                    "type": "single",
                    "display": "text-below",
                    "sources": [
                        {
                            "id": "src-399a00936e39",
                            "name": "Server 1",
                            "contents": [
                                {
                                    "id": "ct-54a247a22ed0",
                                    "name": "cong-an-ho-chi-minh-city-vs-becamex-ho-chi-minh-city-2398356",
                                    "streams": [
                                        {
                                            "id": "st-934fdc06e0d3",
                                            "name": "Server 1",
                                            "stream_links": [
                                                {
                                                    "id": "lnk-6c1b32bbf82a",
                                                    "name": "HD",
                                                    "type": "hls",
                                                    "default": true,
                                                    "url": "https://live10.watchsoccerlivenews.net/live/gaonep_key/playlist.m3u8",
                                                    "request_headers": [
                                                        {
                                                            "key": "Referer",
                                                            "value": "https://hoadaotv.org/cong-an-ho-chi-minh-city-vs-becamex-ho-chi-minh-city-2398356"
                                                        },
                                                        {
                                                            "key": "User-Agent",
                                                            "value": "Mozilla/5.0"
                                                        }
                                                    ]
                                                }
                                            ]
                                        }
                                    ]
                                }
                            ]
                        }
                    ]
                },
                {
                    "id": "ch-b315768c57f2",
                    "name": "manchester-united-vs-crystal-palace-2398560",
                    "labels": [
                        {
                            "position": "top-left",
                            "text": "● Live",
                            "color": "#FF0000",
                            "text_color": "#FFFFFF"
                        }
                    ],
                    "description": "Live Stream",
                    "image": {
                        "url": "https://raw.githubusercontent.com/nkqbbg/20251_CNWeb_User_Management/7c0829f097849f9cfc54b5f6f37e2dbddda468c6/hoadaologo.jpg",
                        "height": 480,
                        "width": 640,
                        "display": "cover",
                        "shape": "square"
                    },
                    "type": "single",
                    "display": "text-below",
                    "sources": [
                        {
                            "id": "src-5a658a0511f0",
                            "name": "Server 1",
                            "contents": [
                                {
                                    "id": "ct-56475dc90d84",
                                    "name": "manchester-united-vs-crystal-palace-2398560",
                                    "streams": [
                                        {
                                            "id": "st-51b5d26fba42",
                                            "name": "Server 1",
                                            "stream_links": [
                                                {
                                                    "id": "lnk-6569de1fa54b",
                                                    "name": "HD",
                                                    "type": "hls",
                                                    "default": true,
                                                    "url": "https://live10.watchsoccerlivenews.net/live/buncha/playlist.m3u8",
                                                    "request_headers": [
                                                        {
                                                            "key": "Referer",
                                                            "value": "https://hoadaotv.org/manchester-united-vs-crystal-palace-2398560"
                                                        },
                                                        {
                                                            "key": "User-Agent",
                                                            "value": "Mozilla/5.0"
                                                        }
                                                    ]
                                                }
                                            ]
                                        }
                                    ]
                                }
                            ]
                        }
                    ]
                },
                {
                    "id": "ch-58965176fbfa",
                    "name": "fulham-vs-tottenham-hotspur-2398592",
                    "labels": [
                        {
                            "position": "top-left",
                            "text": "● Live",
                            "color": "#FF0000",
                            "text_color": "#FFFFFF"
                        }
                    ],
                    "description": "Live Stream",
                    "image": {
                        "url": "https://raw.githubusercontent.com/nkqbbg/20251_CNWeb_User_Management/7c0829f097849f9cfc54b5f6f37e2dbddda468c6/hoadaologo.jpg",
                        "height": 480,
                        "width": 640,
                        "display": "cover",
                        "shape": "square"
                    },
                    "type": "single",
                    "display": "text-below",
                    "sources": [
                        {
                            "id": "src-8dbadd49fc59",
                            "name": "Server 1",
                            "contents": [
                                {
                                    "id": "ct-e41f57b333b1",
                                    "name": "fulham-vs-tottenham-hotspur-2398592",
                                    "streams": [
                                        {
                                            "id": "st-7f5c5e2366f3",
                                            "name": "Server 1",
                                            "stream_links": [
                                                {
                                                    "id": "lnk-8ca635f50d54",
                                                    "name": "HD",
                                                    "type": "hls",
                                                    "default": true,
                                                    "url": "https://live10.watchsoccerlivenews.net/live/chimnho_key/playlist.m3u8",
                                                    "request_headers": [
                                                        {
                                                            "key": "Referer",
                                                            "value": "https://hoadaotv.org/fulham-vs-tottenham-hotspur-2398592"
                                                        },
                                                        {
                                                            "key": "User-Agent",
                                                            "value": "Mozilla/5.0"
                                                        }
                                                    ]
                                                }
                                            ]
                                        }
                                    ]
                                }
                            ]
                        }
                    ]
                },
                {
                    "id": "ch-12a77ebd8e3d",
                    "name": "brighton-hove-albion-vs-nottingham-forest-2398595",
                    "labels": [
                        {
                            "position": "top-left",
                            "text": "● Live",
                            "color": "#FF0000",
                            "text_color": "#FFFFFF"
                        }
                    ],
                    "description": "Live Stream",
                    "image": {
                        "url": "https://raw.githubusercontent.com/nkqbbg/20251_CNWeb_User_Management/7c0829f097849f9cfc54b5f6f37e2dbddda468c6/hoadaologo.jpg",
                        "height": 480,
                        "width": 640,
                        "display": "cover",
                        "shape": "square"
                    },
                    "type": "single",
                    "display": "text-below",
                    "sources": [
                        {
                            "id": "src-133e87a0ab72",
                            "name": "Server 1",
                            "contents": [
                                {
                                    "id": "ct-8af426695235",
                                    "name": "brighton-hove-albion-vs-nottingham-forest-2398595",
                                    "streams": [
                                        {
                                            "id": "st-ce49507eb493",
                                            "name": "Server 1",
                                            "stream_links": [
                                                {
                                                    "id": "lnk-ddaf4b71ba1c",
                                                    "name": "HD",
                                                    "type": "hls",
                                                    "default": true,
                                                    "url": "https://live10.watchsoccerlivenews.net/live/meobeo_key/playlist.m3u8",
                                                    "request_headers": [
                                                        {
                                                            "key": "Referer",
                                                            "value": "https://hoadaotv.org/brighton-hove-albion-vs-nottingham-forest-2398595"
                                                        },
                                                        {
                                                            "key": "User-Agent",
                                                            "value": "Mozilla/5.0"
                                                        }
                                                    ]
                                                }
                                            ]
                                        }
                                    ]
                                }
                            ]
                        }
                    ]
                }
            ]
        }
    ],
    "option": {
        "save_history": false,
        "save_search_history": false,
        "save_wishlist": false
    }
}